wk/__init__.py
wk/cli.py
wk/pkg_info.py
wk/utils.py
wk/applications/__init__.py
wk/applications/reademe.md
wk/applications/fsapp/__init__.py
wk/applications/fsapp/setup.py
wk/applications/fsapp/pjfiles/__init__.py
wk/applications/fsapp/pjfiles/main.py
wk/applications/zspt/__init__.py
wk/applications/zspt/setup.py
wk/applications/zspt/pjfiles/__init__.py
wk/applications/zspt/pjfiles/config.cfg
wk/applications/zspt/pjfiles/main.py
wk/applications/zspt/pjfiles/windows.cfg
wk/basic/__init__.py
wk/basic/math_utils.py
wk/basic/other_utils.py
wk/basic/string_utils.py
wk/basic/time_utils.py
wk/basic/types.py
wk/basic/types2.py
wk/cv/__init__.py
wk/cv/models/__init__.py
wk/cv/models/resnet/__init__.py
wk/cv/models/resnet/predict.py
wk/cv/models/resnet/test.py
wk/cv/models/resnet/train.py
wk/cv/models/resnet/val.py
wk/cv/utils/__init__.py
wk/cv/utils/boxutils.py
wk/cv/utils/dataset.py
wk/cv/utils/imutils.py
wk/cv/utils/augmentations/__init__.py
wk/cv/utils/augmentations/object_detection.py
wk/cv/utils/augmentations/trans.py
wk/cv/utils/extra/__init__.py
wk/cv/utils/extra/get_table.py
wk/cv/utils/extra/rectify.py
wk/data/__init__.py
wk/data/__pycache__/__init__.cpython-37.pyc
wk/data/documents/README.md
wk/data/modules/login/LoginPage.tem
wk/data/modules/login/MessagePage.tem
wk/data/modules/login/RegisterPage.tem
wk/data/modules/login/base.tem
wk/data/modules/login/com.js
wk/data/modules/login/config.tem
wk/data/modules/login/login_register.js
wk/data/modules/login/urls.tem
wk/data/modules/login/utils.js
wk/data/modules/login/imgs/qq.png
wk/data/parts/base.tem
wk/data/parts/js/com.js
wk/data/parts/js/utils.js
wk/data/static/README.md
wk/data/static/css/bootstrap.min.css
wk/data/static/css/hljs/default.css
wk/data/static/imgs/bg.jpg
wk/data/static/imgs/icon/qq.png
wk/data/static/imgs/icon/svg/clock-orange.svg
wk/data/static/imgs/icon/svg/zsk.svg
wk/data/static/imgs/icon/svg/zsyl.svg
wk/data/static/js/bootstrap.min.js
wk/data/static/js/highlight.js
wpkit2-0.0.4.1.dist-info/LICENSE
wpkit2-0.0.4.1.dist-info/METADATA
wpkit2-0.0.4.1.dist-info/WHEEL
wpkit2-0.0.4.1.dist-info/entry_points.txt
wpkit2-0.0.4.1.dist-info/top_level.txt
wpkit2-0.0.4.1.dist-info/RECORD
